Workbook

Sheet Assumptions
A1: MODEL ASSUMPTIONS — edit the blue cells, everything recalculates
A3: Parameter | B3: Value | C3: Source / Justification
A4: Total customers scored | B4: 5265 | C4: Output of the Random Forest churn model
A5: High-risk customers | B5: 2561 | C5: Predicted churn probability > 0.70
A6: Avg annual spend, at-risk seg. | B6: 934.67257 | C6: Mean historical spend of the high-risk cohort
A7: Total revenue at risk | B7: 2393696.5 | C7: Sum of historical spend across high-risk customers
A8: Campaign cost per customer | B8: 15 | C8: ASSUMPTION: email + offer fulfilment cost
A9: Win-back success rate (base) | B9: 0.25 | C9: ASSUMPTION: industry benchmark for retail win-back
A10: Discount offered to re-engage | B10: 0.1 | C10: ASSUMPTION: margin given up to trigger return
A11: Conservative success rate | B11: 0.15 | C11: ASSUMPTION: downside scenario
A12: Optimistic success rate | B12: 0.35 | C12: ASSUMPTION: upside scenario
A14: Grey rows are computed from the model output. Blue rows are business assumptions chosen by the analyst — change them and every sheet updates.

Sheet Intervention ROI
A1: WIN-BACK CAMPAIGN — ROI MODEL
A2: Question: is it worth running a win-back campaign against the high-risk cohort, and what success rate does it need to break even?
A4: Metric | B4: Conservative | C4: Base Case | D4: Optimistic | E4: Notes
A5: Customers targeted | B5: =Assumptions!$B$5 -> 2561 | C5: =Assumptions!$B$5 -> 2561 | D5: =Assumptions!$B$5 -> 2561 | E5: Entire high-risk cohort
A6: Assumed success rate | B6: =Assumptions!$B$11 -> 0.15 | C6: =Assumptions!$B$9 -> 0.25 | D6: =Assumptions!$B$12 -> 0.35 | E6: Share of contacted customers who return
A7: Expected customers recovered | B7: =B5*B6 -> 384.15 | C7: =C5*C6 -> 640.25 | D7: =D5*D6 -> 896.35 | E7: Targeted x success rate
A8: Gross revenue recovered | B8: =B7*Assumptions!$B$6 -> 359054.47 | C8: =C7*Assumptions!$B$6 -> 598424.11 | D8: =D7*Assumptions!$B$6 -> 837793.76 | E8: Recovered customers x avg annual spend
A9: Less: discount given | B9: =-B8*Assumptions!$B$10 -> -35905.447 | C9: =-C8*Assumptions!$B$10 -> -59842.412 | D9: =-D8*Assumptions!$B$10 -> -83779.376 | E9: Margin sacrificed to trigger return
A10: Less: campaign cost | B10: =-B5*Assumptions!$B$8 -> -38415 | C10: =-C5*Assumptions!$B$8 -> -38415 | D10: =-D5*Assumptions!$B$8 -> -38415 | E10: Cost of contacting every targeted customer
A11: Net benefit | B11: =B8+B9+B10 -> 284734.02 | C11: =C8+C9+C10 -> 500166.7 | D11: =D8+D9+D10 -> 715599.38 | E11: Revenue recovered minus all costs
A12: Total campaign cost | B12: =B5*Assumptions!$B$8 -> 38415 | C12: =C5*Assumptions!$B$8 -> 38415 | D12: =D5*Assumptions!$B$8 -> 38415 | E12: Denominator for ROI
A13: ROI | B13: =B11/B12 -> 7.4120532 | C13: =C11/C12 -> 13.020089 | D13: =D11/D12 -> 18.628124 | E13: Net benefit / campaign spend
A14: Break-even success rate | B14: =Assumptions!$B$8/(Assumptions!$B$6*(1-Assumptions!$B$10)) -> 0.017831556 | C14: =Assumptions!$B$8/(Assumptions!$B$6*(1-Assumptions!$B$10)) -> 0.017831556 | D14: =Assumptions!$B$8/(Assumptions!$B$6*(1-Assumptions!$B$10)) -> 0.017831556 | E14: Minimum success rate for the campaign to pay for itself
A16: HOW TO READ THIS: The break-even success rate is the single most useful number here. If the campaign can realistically beat it, the campaign is worth running. If it cannot, the correct decision is not to run it — the model's value is telling you that before you spend the budget, not after.

Sheet Sensitivity
A1: SENSITIVITY — NET BENEFIT ACROSS SUCCESS RATES
A2: The base case assumes one success rate. This grid shows what happens across the plausible range, so the decision isn't hostage to a single assumption.
A4: Success rate → | B4: 5% | C4: 10% | D4: 15% | E4: 20% | F4: 25% | G4: 30% | H4: 40%
A5: Rate | B5: 0.05 | C5: 0.1 | D5: 0.15 | E5: 0.2 | F5: 0.25 | G5: 0.3 | H5: 0.4
A6: Customers recovered | B6: =Assumptions!$B$5*B5 -> 128.05 | C6: =Assumptions!$B$5*C5 -> 256.1 | D6: =Assumptions!$B$5*D5 -> 384.15 | E6: =Assumptions!$B$5*E5 -> 512.2 | F6: =Assumptions!$B$5*F5 -> 640.25 | G6: =Assumptions!$B$5*G5 -> 768.3 | H6: =Assumptions!$B$5*H5 -> 1024.4
A7: Gross revenue recovered | B7: =B6*Assumptions!$B$6 -> 119684.82 | C7: =C6*Assumptions!$B$6 -> 239369.65 | D7: =D6*Assumptions!$B$6 -> 359054.47 | E7: =E6*Assumptions!$B$6 -> 478739.29 | F7: =F6*Assumptions!$B$6 -> 598424.11 | G7: =G6*Assumptions!$B$6 -> 718108.94 | H7: =H6*Assumptions!$B$6 -> 957478.58
A8: Net benefit | B8: =B7*(1-Assumptions!$B$10)-Assumptions!$B$5*Assumptions!$B$8 -> 69301.341 | C8: =C7*(1-Assumptions!$B$10)-Assumptions!$B$5*Assumptions!$B$8 -> 177017.68 | D8: =D7*(1-Assumptions!$B$10)-Assumptions!$B$5*Assumptions!$B$8 -> 284734.02 | E8: =E7*(1-Assumptions!$B$10)-Assumptions!$B$5*Assumptions!$B$8 -> 392450.36 | F8: =F7*(1-Assumptions!$B$10)-Assumptions!$B$5*Assumptions!$B$8 -> 500166.7 | G8: =G7*(1-Assumptions!$B$10)-Assumptions!$B$5*Assumptions!$B$8 -> 607883.04 | H8: =H7*(1-Assumptions!$B$10)-Assumptions!$B$5*Assumptions!$B$8 -> 823315.73
A9: ROI | B9: =B8/(Assumptions!$B$5*Assumptions!$B$8) -> 1.8040177 | C9: =C8/(Assumptions!$B$5*Assumptions!$B$8) -> 4.6080354 | D9: =D8/(Assumptions!$B$5*Assumptions!$B$8) -> 7.4120532 | E9: =E8/(Assumptions!$B$5*Assumptions!$B$8) -> 10.216071 | F9: =F8/(Assumptions!$B$5*Assumptions!$B$8) -> 13.020089 | G9: =G8/(Assumptions!$B$5*Assumptions!$B$8) -> 15.824106 | H9: =H8/(Assumptions!$B$5*Assumptions!$B$8) -> 21.432142
A11: Read across the 'Net benefit' row to find where it crosses zero. That crossing point is the break-even success rate — everything to the right is profitable, everything to the left destroys value.

Sheet Risk Segments
A1: CUSTOMER BASE BY CHURN RISK BAND
A3: Risk Band | B3: Customers | C3: % of Base | D3: Revenue Represented | E3: Avg Spend | F3: Recommended Action
A4: High | B4: 2561 | C4: 0.48641975 | D4: 2393696.5 | E4: 934.67257 | F4: Targeted win-back campaign — highest urgency
A5: Medium | B5: 545 | C5: 0.10351377 | D5: 1084640.9 | E5: 1990.1668 | F5: Monitor; low-cost re-engagement (newsletter, offers)
A6: Low | B6: 2119 | C6: 0.40246914 | D6: 11287499 | E6: 5326.8046 | F6: No intervention needed — protect via normal service
A7: TOTAL | B7: 5265 | C7: 1 | D7: 16686560 | E7: 3169.3372
